LICENSE
MANIFEST.in
setup.cfg
setup.py
tryhaskell/__init__.py
tryhaskell/__main__.py
tryhaskell.egg-info/PKG-INFO
tryhaskell.egg-info/SOURCES.txt
tryhaskell.egg-info/dependency_links.txt
tryhaskell.egg-info/requires.txt
tryhaskell.egg-info/top_level.txt