Metadata-Version: 1.0
Name: tryhaskell
Version: 0.1.0
Summary: Python client for tryhaskell.org
Home-page: https://github.com/carymrobbins/py-tryhaskell
Author: Cary Robbins
Author-email: carymrobbins@gmail.com
License: BSD3
Platform: UNKNOWN
